{
  "source_url": "https://discourse.mcneel.com/t/why-is-this-method-wrong-in-python/120924",
  "topic_id": 120924,
  "title": "Why is this method wrong in Python?",
  "question": "Hello! Forum!\n\n\nIn C#, the right method is wrong in Python. How can I use it in Python?\n\n\npythonques.gh\n (3.6 KB)",
  "code_blocks": [
    {
      "code": "import Rhino.Geometry as rg\nfrom System.Collections.Generic import List\na = x.Split(List[rg.Curve](y), 0.01)",
      "language": "python",
      "author": "Mahdiyar",
      "post_number": 2,
      "is_solution": false
    }
  ],
  "tags": [
    "csharp",
    "file-io",
    "geometry",
    "python",
    "rhinocommon"
  ],
  "has_accepted_answer": false,
  "category_id": 8,
  "posts_count": 4,
  "views": 343
}