{
  "source_url": "https://discourse.mcneel.com/t/scripteditor-autocomplete-fails/198188",
  "topic_id": 198188,
  "title": "ScriptEditor Autocomplete fails",
  "question": "Hi \n@eirannejad\n,\n\n\nit seems that autocomplete fails on many of my scripts after a certain level:\n\n\n\n\nit does not happen on a new empty script, but if the script has a bit of complexity, it fails quite often.\n\n\n_\n\nc.",
  "code_blocks": [
    {
      "code": "#! python3\nimport scriptcontext as sc\nfrom Rhino import RhinoDoc\n\ndoc: RhinoDoc = sc.doc\ndoc.Objects.",
      "language": "python",
      "author": "eirannejad",
      "post_number": 3,
      "is_solution": false
    }
  ],
  "tags": [
    "file-io",
    "python"
  ],
  "has_accepted_answer": false,
  "category_id": 11,
  "posts_count": 2,
  "views": 66
}