{
  "source_url": "https://discourse.mcneel.com/t/python-center-box/67767",
  "topic_id": 67767,
  "title": "Python center box",
  "question": "Does there exist something like a python center box?\n\nI can easily fix the problem in the image, but I want to be sure that I am not working inefficient.\n\n\n0100 python centerbox.gh\n (8.6 KB)\n\n\n\n\n0100%20python%20centerbox\n1428×700 59.6 KB",
  "code_blocks": [
    {
      "code": "boxPts = []\nboxPts.append(rs.VectorAdd(b, (x/2, y/2, -z/2)))\nboxPts.append(rs.VectorAdd(b, (x/2, -y/2, -z/2)))\nboxPts.append(rs.VectorAdd(b, (-x/2, -y/2, -z/2)))\nboxPts.append(rs.VectorAdd(b, (-x/2, y/2, -z/2)))\nboxPts.append(rs.VectorAdd(b, (x/2, y/2, z/2)))\nboxPts.append(rs.VectorAdd(b, (x/2, -y/2, z/2)))\nboxPts.append(rs.VectorAdd(b, (-x/2, -y/2, z/2)))\nboxPts.append(rs.VectorAdd(b, (-x/2, y/2, z/2)))\na = rs.AddBox(boxPts)",
      "language": "python",
      "author": "Amir_Touhidi",
      "post_number": 2,
      "is_solution": false
    },
    {
      "code": "import Rhino.Geometry as rg\n\nbox = rg.Box(\n    plane,\n    rg.Interval(-0.5*x,0.5*x),\n    rg.Interval(-0.5*y,0.5*y),\n    rg.Interval(-0.5*z,0.5*z))\n\na = box;",
      "language": "python",
      "author": "TomTom",
      "post_number": 3,
      "is_solution": false
    },
    {
      "code": "import Rhino.Geometry as rg\n\nplaneBox = rg.Plane(\n    rg.Point3d (4.0,2.0,1.0),   # Origin\n    rg.Vector3d(1.0,0.2,0.0),   # xAxis    \n    rg.Vector3d(0.2,1.0,0.0))   # yAxis    \n\n(Other overloads are possible)",
      "language": "python",
      "author": "TomTom",
      "post_number": 5,
      "is_solution": false
    }
  ],
  "tags": [
    "file-io",
    "geometry",
    "python",
    "rhinocommon"
  ],
  "has_accepted_answer": false,
  "category_id": 2,
  "posts_count": 6,
  "views": 2094
}